{
  "title": "Quiz de la Lección 5",
  "questions": [
    {
      "question": "¿Qué es una 'Pregunta Suave' para la Autoridad?",
      "options": [
        {
          "id": "a",
          "text": "Déjame hablar con tu jefe"
        },
        {
          "id": "b",
          "text": "¿Eres el pasante?"
        },
        {
          "id": "c",
          "text": "¿Quién más necesitaría estar involucrado en evaluar esta solución?"
        },
        {
          "id": "d",
          "text": "¿Puedes firmar esto hoy?"
        }
      ],
      "correctAnswer": "c",
      "explanation": "Esta pregunta respeta al prospecto mientras descubre a los demás stakeholders y tomadores de decisiones en el ecosistema.",
      "id": "q1",
      "type": "multiple-choice"
    },
    {
      "question": "¿Por qué '¿Por qué mirar esto AHORA?' es una pregunta de Necesidad crítica?",
      "options": [
        {
          "id": "a",
          "text": "Porque te dice el Evento Convincente / Disparador"
        },
        {
          "id": "b",
          "text": "Porque muestra que eres curioso"
        },
        {
          "id": "c",
          "text": "Porque llena tiempo"
        },
        {
          "id": "d",
          "text": "Porque te ayuda a comparar competidores"
        }
      ],
      "correctAnswer": "a",
      "explanation": "Si el problema ha existido durante años pero te están llamando hoy, algo cambió. Identificar ese 'Disparador' te da el apalancamiento para cerrar.",
      "id": "q2",
      "type": "multiple-choice"
    },
    {
      "question": "El guión de cronograma de 'Trabajar hacia Atrás' ayuda porque:",
      "options": [
        {
          "id": "a",
          "text": "Te ayuda a planificar tus vacaciones"
        },
        {
          "id": "b",
          "text": "Ancla la fecha de cierre al objetivo de NEGOCIO DE ELLOS, no a tu cuota"
        },
        {
          "id": "c",
          "text": "Te hace ver organizado"
        },
        {
          "id": "d",
          "text": "Confunde al prospecto"
        }
      ],
      "correctAnswer": "b",
      "explanation": "Si necesitan que esté activo para la fecha X, y la implementación toma Y semanas, la lógica dicta que deben firmar para la fecha Z. No los estás presionando; el calendario lo hace.",
      "id": "q3",
      "type": "multiple-choice"
    },
    {
      "question": "¿Cuál es el riesgo de preguntar '¿Tienes presupuesto?' directamente a una empresa en etapa temprana?",
      "options": [
        {
          "id": "a",
          "text": "Pueden decir que sí"
        },
        {
          "id": "b",
          "text": "Probablemente no tienen una partida específica para 'Tu Herramienta', así que dirán 'No' aunque tengan dinero"
        },
        {
          "id": "c",
          "text": "Se ofenderán"
        },
        {
          "id": "d",
          "text": "Colgarán"
        }
      ],
      "correctAnswer": "b",
      "explanation": "Las startups financian las cosas dinámicamente. Preguntar sobre una partida rígida produce un Falso Negativo. Preguntar '¿Cómo se financia esto?' permite respuestas creativas.",
      "id": "q4",
      "type": "multiple-choice"
    },
    {
      "question": "¿Cómo pruebas el 'Costo de la Inacción'?",
      "options": [
        {
          "id": "a",
          "text": "Preguntar: '¿Qué pasa si no arreglas esto para el próximo trimestre?'"
        },
        {
          "id": "b",
          "text": "Preguntar: '¿Cuánto cuesta esto?'"
        },
        {
          "id": "c",
          "text": "Preguntar: '¿Te gustan nuestros precios?'"
        },
        {
          "id": "d",
          "text": "Preguntar: '¿Es esto importante?'"
        }
      ],
      "correctAnswer": "a",
      "explanation": "Esta pregunta los obliga a articular el dolor de no hacer nada. Si la respuesta es 'No pasa nada', no hay negocio.",
      "id": "q5",
      "type": "multiple-choice"
    }
  ],
  "sectionId": "sales-methodology",
  "courseId": "discovery-framework",
  "lessonId": "5"
}
