{
    "lessonId": "4",
    "courseId": "sales-psychology",
    "sectionId": "foundations",
    "title": "The Price of Underpricing",
    "questions": [
        {
            "id": "q1",
            "type": "multiple-choice",
            "question": "Research suggests what percentage of entrepreneurs experience imposter syndrome?",
            "options": [
                {
                    "id": "opt1",
                    "text": "25%"
                },
                {
                    "id": "opt2",
                    "text": "50%"
                },
                {
                    "id": "opt3",
                    "text": "84%"
                },
                {
                    "id": "opt4",
                    "text": "99%"
                }
            ],
            "correctAnswer": "opt3",
            "explanation": "84% of entrepreneurs report feelings of imposter syndrome, which directly impacts their pricing decisions."
        },
        {
            "id": "q2",
            "type": "multiple-choice",
            "question": "Psychologically, why do founders underprice their products?",
            "options": [
                {
                    "id": "opt1",
                    "text": "To serve the community"
                },
                {
                    "id": "opt2",
                    "text": "As a shield against the risk of rejection"
                },
                {
                    "id": "opt3",
                    "text": "Because their costs are low"
                },
                {
                    "id": "opt4",
                    "text": "To avoiding taxes"
                }
            ],
            "correctAnswer": "opt2",
            "explanation": "Low prices lower the stakes. If someone rejects a cheap product, it doesn't feel like a judgment of your worth. A high price invites judgment."
        },
        {
            "id": "q3",
            "type": "multiple-choice",
            "question": "What is a negative consequence of setting your price too low in B2B?",
            "options": [
                {
                    "id": "opt1",
                    "text": "You signal a lack of credibility or enterprise-readiness"
                },
                {
                    "id": "opt2",
                    "text": "You make too much money too fast"
                },
                {
                    "id": "opt3",
                    "text": "Customers act too respectful"
                },
                {
                    "id": "opt4",
                    "text": "Competitors will sue you"
                }
            ],
            "correctAnswer": "opt1",
            "explanation": "In B2B, price is often a proxy for quality. A price that is too low can signal that your solution is a 'toy' rather than a serious business tool."
        },
        {
            "id": "q4",
            "type": "multiple-choice",
            "question": "Who are generally the most demanding customers?",
            "options": [
                {
                    "id": "opt1",
                    "text": "Enterprise clients paying $50k+"
                },
                {
                    "id": "opt2",
                    "text": "Price-sensitive buyers paying the lowest tier"
                },
                {
                    "id": "opt3",
                    "text": "Investors"
                },
                {
                    "id": "opt4",
                    "text": "Partners"
                }
            ],
            "correctAnswer": "opt2",
            "explanation": "Buyers who value money over time (price sensitive) tend to have higher expectations for support and attention relative to what they pay."
        },
        {
            "id": "q5",
            "type": "multiple-choice",
            "question": "What happened in the 'Fractional Consulting' case study when Mike raised his prices 5x?",
            "options": [
                {
                    "id": "opt1",
                    "text": "He lost all his clients and went broke"
                },
                {
                    "id": "opt2",
                    "text": "He kept all his clients and made 5x more"
                },
                {
                    "id": "opt3",
                    "text": "He lost 80% of clients but made the same revenue with 20% of the work"
                },
                {
                    "id": "opt4",
                    "text": "He got sued"
                }
            ],
            "correctAnswer": "opt3",
            "explanation": "Raising prices is a filter. It removed the low-value clients and allowed him to earn the same revenue with significantly less workload."
        }
    ],
    "passingScore": 70
}